{
	"url": "https://api.github.com/repos/mlavergn/rxgo/releases/23085283",
	"assets_url": "https://api.github.com/repos/mlavergn/rxgo/releases/23085283/assets",
	"upload_url": "https://uploads.github.com/repos/mlavergn/rxgo/releases/23085283/assets{?name,label}",
	"html_url": "https://github.com/mlavergn/rxgo/releases/tag/v0.36.1",
	"id": 23085283,
	"node_id": "MDc6UmVsZWFzZTIzMDg1Mjgz",
	"tag_name": "v0.36.1",
	"target_commitish": "master",
	"name": "0.36.1 - RxGo",
	"draft": false,
	"author": {
		"login": "mlavergn",
		"id": 80546,
		"node_id": "MDQ6VXNlcjgwNTQ2",
		"avatar_url": "https://avatars3.githubusercontent.com/u/80546?v=4",
		"gravatar_id": "",
		"url": "https://api.github.com/users/mlavergn",
		"html_url": "https://github.com/mlavergn",
		"followers_url": "https://api.github.com/users/mlavergn/followers",
		"following_url": "https://api.github.com/users/mlavergn/following{/other_user}",
		"gists_url": "https://api.github.com/users/mlavergn/gists{/gist_id}",
		"starred_url": "https://api.github.com/users/mlavergn/starred{/owner}{/repo}",
		"subscriptions_url": "https://api.github.com/users/mlavergn/subscriptions",
		"organizations_url": "https://api.github.com/users/mlavergn/orgs",
		"repos_url": "https://api.github.com/users/mlavergn/repos",
		"events_url": "https://api.github.com/users/mlavergn/events{/privacy}",
		"received_events_url": "https://api.github.com/users/mlavergn/received_events",
		"type": "User",
		"site_admin": false
	},
	"prerelease": false,
	"created_at": "2020-01-23T20:19:28Z",
	"published_at": "2020-01-23T20:20:29Z",
	"assets": [
		{
			"url": "https://api.github.com/repos/mlavergn/rxgo/releases/assets/17537197",
			"id": 17537197,
			"node_id": "MDEyOlJlbGVhc2VBc3NldDE3NTM3MTk3",
			"name": "rxgo.zip",
			"label": "",
			"uploader": {
				"login": "mlavergn",
				"id": 80546,
				"node_id": "MDQ6VXNlcjgwNTQ2",
				"avatar_url": "https://avatars3.githubusercontent.com/u/80546?v=4",
				"gravatar_id": "",
				"url": "https://api.github.com/users/mlavergn",
				"html_url": "https://github.com/mlavergn",
				"followers_url": "https://api.github.com/users/mlavergn/followers",
				"following_url": "https://api.github.com/users/mlavergn/following{/other_user}",
				"gists_url": "https://api.github.com/users/mlavergn/gists{/gist_id}",
				"starred_url": "https://api.github.com/users/mlavergn/starred{/owner}{/repo}",
				"subscriptions_url": "https://api.github.com/users/mlavergn/subscriptions",
				"organizations_url": "https://api.github.com/users/mlavergn/orgs",
				"repos_url": "https://api.github.com/users/mlavergn/repos",
				"events_url": "https://api.github.com/users/mlavergn/events{/privacy}",
				"received_events_url": "https://api.github.com/users/mlavergn/received_events",
				"type": "User",
				"site_admin": false
			},
			"content_type": "application/octet-stream",
			"state": "uploaded",
			"size": 19954,
			"download_count": 0,
			"created_at": "2020-01-23T20:20:30Z",
			"updated_at": "2020-01-23T20:20:30Z",
			"browser_download_url": "https://github.com/mlavergn/rxgo/releases/download/v0.36.1/rxgo.zip"
		}
	],
	"tarball_url": "https://api.github.com/repos/mlavergn/rxgo/tarball/v0.36.1",
	"zipball_url": "https://api.github.com/repos/mlavergn/rxgo/zipball/v0.36.1",
	"body": ""
}